wow_ai_cv/__init__.py
wow_ai_cv/classification/__init__.py
wow_ai_cv/classification/core.py
wow_ai_cv/dataset/__init__.py
wow_ai_cv/dataset/core.py
wow_ai_cv/dataset/formats/__init__.py
wow_ai_cv/dataset/formats/coco.py
wow_ai_cv/dataset/formats/pascal_voc.py
wow_ai_cv/dataset/formats/yolo.py
wow_ai_cv/dataset/ultils.py
wow_ai_cv/detection/__init__.py
wow_ai_cv/detection/annotate.py
wow_ai_cv/detection/core.py
wow_ai_cv/detection/line_counter.py
wow_ai_cv/detection/tools/__init__.py
wow_ai_cv/detection/tools/polygon_zone.py
wow_ai_cv/detection/utils.py
wow_ai_cv/draw/__init__.py
wow_ai_cv/draw/color.py
wow_ai_cv/draw/utils.py
wow_ai_cv/geometry/__init__.py
wow_ai_cv/geometry/core.py
wow_ai_cv/geometry/utils.py
wow_ai_cv/utils/__init__.py
wow_ai_cv/utils/file.py
wow_ai_cv/utils/image.py
wow_ai_cv/utils/internal.py
wow_ai_cv/utils/notebook.py
wow_ai_cv/utils/video.py
wow_ai_cv-0.6.0.dist-info/LICENSE.md
wow_ai_cv-0.6.0.dist-info/METADATA
wow_ai_cv-0.6.0.dist-info/WHEEL
wow_ai_cv-0.6.0.dist-info/RECORD
